odoo/addons/fastapi_encrypted_errors/README.rst
odoo/addons/fastapi_encrypted_errors/__init__.py
odoo/addons/fastapi_encrypted_errors/__manifest__.py
odoo/addons/fastapi_encrypted_errors/fastapi_dispatcher.py
odoo/addons/fastapi_encrypted_errors/i18n/fastapi_encrypted_errors.pot
odoo/addons/fastapi_encrypted_errors/i18n/it.po
odoo/addons/fastapi_encrypted_errors/models/__init__.py
odoo/addons/fastapi_encrypted_errors/models/fastapi_endpoint.py
odoo/addons/fastapi_encrypted_errors/readme/CONTRIBUTORS.rst
odoo/addons/fastapi_encrypted_errors/readme/DESCRIPTION.rst
odoo/addons/fastapi_encrypted_errors/readme/USAGE.rst
odoo/addons/fastapi_encrypted_errors/security/ir.model.access.csv
odoo/addons/fastapi_encrypted_errors/static/description/icon.png
odoo/addons/fastapi_encrypted_errors/static/description/index.html
odoo/addons/fastapi_encrypted_errors/tests/__init__.py
odoo/addons/fastapi_encrypted_errors/tests/test_fastapi_encrypted_errors.py
odoo/addons/fastapi_encrypted_errors/views/fastapi_endpoint_views.xml
odoo/addons/fastapi_encrypted_errors/wizards/__init__.py
odoo/addons/fastapi_encrypted_errors/wizards/wizard_fastapi_decrypt_errors.py
odoo/addons/fastapi_encrypted_errors/wizards/wizard_fastapi_decrypt_errors_views.xml
odoo_addon_fastapi_encrypted_errors-16.0.1.0.1.2.dist-info/METADATA
odoo_addon_fastapi_encrypted_errors-16.0.1.0.1.2.dist-info/WHEEL
odoo_addon_fastapi_encrypted_errors-16.0.1.0.1.2.dist-info/top_level.txt
odoo_addon_fastapi_encrypted_errors-16.0.1.0.1.2.dist-info/RECORD
