Metadata-Version: 2.1
Name: odoo-addon-fastapi_encrypted_errors
Version: 16.0.1.0.1.2
Summary: Adds encrypted error messages to FastAPI error responses.
Home-page: https://github.com/OCA/rest-framework
Author: Akretion,Odoo Community Association (OCA)
Author-email: support@odoo-community.org
License: AGPL-3
Classifier: Programming Language :: Python
Classifier: Framework :: Odoo
Classifier: Framework :: Odoo :: 16.0
Classifier: License :: OSI Approved :: GNU Affero General Public License v3
Requires-Python: >=3.10
Requires-Dist: cryptography
Requires-Dist: odoo-addon-fastapi<16.1dev,>=16.0dev
Requires-Dist: odoo<16.1dev,>=16.0a
